{"2024-09-03":[{"url":"https://www.amazon.eg/dp/B09P2WZN3C","prevPrice":"525.16","currentPrice":197},{"url":"https://www.amazon.eg/dp/B006L76CQ2","prevPrice":"499.00","currentPrice":349},{"url":"https://www.amazon.eg/dp/B013ICMXU6","prevPrice":"440.00","currentPrice":249},{"url":"https://www.amazon.eg/dp/B0B5XXQKCR","prevPrice":"48.62","currentPrice":32},{"url":"https://www.amazon.eg/dp/B07FZPPXHQ","prevPrice":"111.00","currentPrice":0},{"url":"https://www.amazon.eg/dp/B07RRQY8F5","prevPrice":"299.00","currentPrice":179},{"url":"https://www.amazon.eg/dp/B0CQ57SZ7F","prevPrice":"369.00","currentPrice":230},{"url":"https://www.amazon.eg/dp/B0CVFW6C2S","prevPrice":"43.12","currentPrice":23},{"url":"https://www.amazon.eg/dp/B0B42NRDM2","prevPrice":"550.00","currentPrice":341.75},{"url":"https://www.amazon.eg/dp/B09S19N7TQ","prevPrice":"18.05","currentPrice":7.79},{"url":"https://www.amazon.eg/dp/B01MDOVYQ3","prevPrice":"800.00","currentPrice":467.98},{"url":"https://www.amazon.eg/dp/B0BN7LFKFR","prevPrice":"82.00","currentPrice":42},{"url":"https://www.amazon.eg/dp/B0C9MCQHZJ","prevPrice":"14.38","currentPrice":8},{"url":"https://www.amazon.eg/dp/B08WJN9JDK","prevPrice":"149.00","currentPrice":96},{"url":"https://www.amazon.eg/dp/B089T1FCV2","prevPrice":"279.87","currentPrice":164},{"url":"https://www.amazon.eg/dp/B09R252JJT","prevPrice":"23.66","currentPrice":15},{"url":"https://www.amazon.eg/dp/B0CVFW7RQ9","prevPrice":"42.60","currentPrice":23},{"url":"https://www.amazon.eg/dp/B07G9KT4LL","prevPrice":"422.00","currentPrice":12.05},{"url":"https://www.amazon.eg/dp/B0C7H6VYXQ","prevPrice":"18.66","currentPrice":6.6},{"url":"https://www.amazon.eg/dp/B09SBS7TQJ","prevPrice":"19.25","currentPrice":0},{"url":"https://www.amazon.eg/dp/B091J42B1S","prevPrice":"69.99","currentPrice":48},{"url":"https://www.amazon.eg/dp/B09SFGV51J","prevPrice":"39.00","currentPrice":27},{"url":"https://www.amazon.eg/dp/B0C4PSVDBW","prevPrice":"308.00","currentPrice":183},{"url":"https://www.amazon.eg/dp/B08WJPQ5GP","prevPrice":"42.00","currentPrice":11.5},{"url":"https://www.amazon.eg/dp/B0BWN1HZ4X","prevPrice":"325.00","currentPrice":200},{"url":"https://www.amazon.eg/dp/B0994PD4VN","prevPrice":"180.00","currentPrice":87},{"url":"https://www.amazon.eg/dp/B0CVFW6VD4","prevPrice":"43.16","currentPrice":23},{"url":"https://www.amazon.eg/dp/B09V51WF73","prevPrice":"65.00","currentPrice":36.25},{"url":"https://www.amazon.eg/dp/B09TN4T7ZG","prevPrice":"246.25","currentPrice":170.5},{"url":"https://www.amazon.eg/dp/B0C9MF4VC4","prevPrice":"17.00","currentPrice":10.95},{"url":"https://www.amazon.eg/dp/B0C74MPMTF","prevPrice":"70.00","currentPrice":31},{"url":"https://www.amazon.eg/dp/B00WUIEC22","prevPrice":"477.00","currentPrice":14.75}],"2024-09-04":[{"url":"https://www.amazon.eg/dp/B09TN4T7ZG","prevPrice":"246.25","currentPrice":170.5},{"url":"https://www.amazon.eg/dp/B0994PD4VN","prevPrice":"180.00","currentPrice":87},{"url":"https://www.amazon.eg/dp/B0C9MF4VC4","prevPrice":"17.00","currentPrice":10.95},{"url":"https://www.amazon.eg/dp/B09S19N7TQ","prevPrice":"18.05","currentPrice":7.79},{"url":"https://www.amazon.eg/dp/B0B5XXQKCR","prevPrice":"48.62","currentPrice":32},{"url":"https://www.amazon.eg/dp/B0C7H6VYXQ","prevPrice":"18.66","currentPrice":6.6},{"url":"https://www.amazon.eg/dp/B097DJ9S78","prevPrice":"160.00","currentPrice":104.95},{"url":"https://www.amazon.eg/dp/B07RRQY8F5","prevPrice":"299.00","currentPrice":179},{"url":"https://www.amazon.eg/dp/B09SFGV51J","prevPrice":"39.00","currentPrice":26.75},{"url":"https://www.amazon.eg/dp/B091J42B1S","prevPrice":"69.99","currentPrice":48},{"url":"https://www.amazon.eg/dp/B08WJJJ9GT","prevPrice":"99.00","currentPrice":37.44},{"url":"https://www.amazon.eg/dp/B08WJN9JDK","prevPrice":"149.00","currentPrice":96},{"url":"https://www.amazon.eg/dp/B0C4PSVDBW","prevPrice":"308.00","currentPrice":183},{"url":"https://www.amazon.eg/dp/B09V51WF73","prevPrice":"65.00","currentPrice":36.25},{"url":"https://www.amazon.eg/dp/B08WJPQ5GP","prevPrice":"42.00","currentPrice":11.5},{"url":"https://www.amazon.eg/dp/B09R252JJT","prevPrice":"23.66","currentPrice":15},{"url":"https://www.amazon.eg/dp/B0CVFW7RQ9","prevPrice":"42.60","currentPrice":23},{"url":"https://www.amazon.eg/dp/B0CQ57SZ7F","prevPrice":"369.00","currentPrice":230},{"url":"https://www.amazon.eg/dp/B0B42NRDM2","prevPrice":"550.00","currentPrice":341.45},{"url":"https://www.amazon.eg/dp/B08WJJFQQ4","prevPrice":"108.50","currentPrice":0}]}